{
  "embeds": [
    {
      "title": "Apply to Join Us!",
      "description": "For your privacy during the hiring process, once you open a ticket it will direct you to an entirely private channel with an application to fill out that is not viewable by anyone but you and hiring staff. \n\nIf you're interested in applying use the command `-ticket open <Character Name>` to start an application.\n\nIf you need help doing this process please tag <@149276780535087104> or <@200324488640987146>.\n\nCommands to start the process can be posted here.\n",
      "color": 12978185,
      "thumbnail": {
        "url": "https://cdn.discordapp.com/attachments/553500373520744449/707946449815601222/logopad2HD.png"
      }
    }
  ],
  "username": "Panic After Dark",
  "avatar_url": "https://cdn.discordapp.com/attachments/553500373520744449/707946449815601222/logopad2HD.png"
}
